<domain type='kvm'>
  <name>win10</name>
  <uuid>570b5884-53dd-40d4-ba63-3fa05aad477f</uuid>
  <metadata>
    <libosinfo:libosinfo xmlns:libosinfo="http://libosinfo.org/xmlns/libvirt/domain/1.0">
      <libosinfo:os id="http://microsoft.com/win/10"/>
    </libosinfo:libosinfo>
  </metadata>
  <memory unit='KiB'>10485760</memory>
  <currentMemory unit='KiB'>10485760</currentMemory>
  <vcpu placement='static'>8</vcpu>
  <os>
    <type arch='x86_64' machine='pc-q35-6.2'>hvm</type>
    <loader readonly='yes' type='pflash'>/run/libvirt/nix-ovmf/OVMF_CODE.fd</loader>
    <nvram>/var/lib/libvirt/qemu/nvram/win10_VARS.fd</nvram>
    <bootmenu enable='yes'/>
  </os>
  <features>
    <acpi/>
    <apic/>
    <hyperv>
      <relaxed state='on'/>
      <vapic state='on'/>
      <spinlocks state='on' retries='8191'/>
    </hyperv>
    <vmport state='off'/>
  </features>
  <cpu mode='host-model' check='none'>
    <topology sockets='1' dies='1' cores='4' threads='2'/>
  </cpu>
  <clock offset='localtime'>
    <timer name='rtc' tickpolicy='catchup'/>
    <timer name='pit' tickpolicy='delay'/>
    <timer name='hpet' present='no'/>
    <timer name='hypervclock' present='yes'/>
  </clock>
  <on_poweroff>destroy</on_poweroff>
  <on_reboot>restart</on_reboot>
  <on_crash>destroy</on_crash>
  <pm>
    <suspend-to-mem enabled='no'/>
    <suspend-to-disk enabled='no'/>
  </pm>
  <devices>
    <emulator>/run/libvirt/nix-emulators/qemu-system-x86_64</emulator>
    <disk type='file' device='cdrom'>
      <driver name='qemu' type='raw'/>
      <source file='/home/muni/Downloads/Win10_21H1_English_x64.iso'/>
      <target dev='sdb' bus='sata'/>
      <readonly/>
      <boot order='2'/>
      <address type='drive' controller='0' bus='0' target='0' unit='1'/>
    </disk>
    <disk type='file' device='cdrom'>
      <driver name='qemu' type='raw'/>
      <source file='/home/muni/Downloads/virtio-win-0.1.215.iso'/>
      <target dev='sdc' bus='sata'/>
      <readonly/>
      <boot order='3'/>
      <address type='drive' controller='0' bus='0' target='0' unit='2'/>
    </disk>
    <disk type='file' device='disk'>
      <driver name='qemu' type='qcow2' cache='writeback'/>
      <source file='/home/muni/.local/share/libvirt/images/win10.qcow2'/>
      <target dev='vda' bus='virtio'/>
      <boot order='1'/>
      <address type='pci' domain='0x0000' bus='0x04' slot='0x00' function='0x0'/>
    </disk>
    <controller type='usb' index='0' model='qemu-xhci' ports='15'>
      <address type='pci' domain='0x0000' bus='0x02' slot='0x00' function='0x0'/>
    </controller>
    <controller type='sata' index='0'>
      <address type='pci' domain='0x0000' bus='0x00' slot='0x1f' function='0x2'/>
    </controller>
    <controller type='pci' index='0' model='pcie-root'/>
    <controller type='pci' index='1' model='pcie-root-port'>
      <model name='pcie-root-port'/>
      <target chassis='1' port='0x10'/>
      <address type='pci' domain='0x0000' bus='0x00' slot='0x02' function='0x0' multifunction='on'/>
    </controller>
    <controller type='pci' index='2' model='pcie-root-port'>
      <model name='pcie-root-port'/>
      <target chassis='2' port='0x11'/>
      <address type='pci' domain='0x0000' bus='0x00' slot='0x02' function='0x1'/>
    </controller>
    <controller type='pci' index='3' model='pcie-root-port'>
      <model name='pcie-root-port'/>
      <target chassis='3' port='0x12'/>
      <address type='pci' domain='0x0000' bus='0x00' slot='0x02' function='0x2'/>
    </controller>
    <controller type='pci' index='4' model='pcie-root-port'>
      <model name='pcie-root-port'/>
      <target chassis='4' port='0x13'/>
      <address type='pci' domain='0x0000' bus='0x00' slot='0x02' function='0x3'/>
    </controller>
    <controller type='pci' index='5' model='pcie-root-port'>
      <model name='pcie-root-port'/>
      <target chassis='5' port='0x14'/>
      <address type='pci' domain='0x0000' bus='0x00' slot='0x02' function='0x4'/>
    </controller>
    <controller type='pci' index='6' model='pcie-root-port'>
      <model name='pcie-root-port'/>
      <target chassis='6' port='0x15'/>
      <address type='pci' domain='0x0000' bus='0x00' slot='0x02' function='0x5'/>
    </controller>
    <controller type='pci' index='7' model='pcie-root-port'>
      <model name='pcie-root-port'/>
      <target chassis='7' port='0x16'/>
      <address type='pci' domain='0x0000' bus='0x00' slot='0x02' function='0x6'/>
    </controller>
    <controller type='pci' index='8' model='pcie-to-pci-bridge'>
      <model name='pcie-pci-bridge'/>
      <address type='pci' domain='0x0000' bus='0x01' slot='0x00' function='0x0'/>
    </controller>
    <controller type='pci' index='9' model='pcie-root-port'>
      <model name='pcie-root-port'/>
      <target chassis='9' port='0x17'/>
      <address type='pci' domain='0x0000' bus='0x00' slot='0x02' function='0x7'/>
    </controller>
    <controller type='virtio-serial' index='0'>
      <address type='pci' domain='0x0000' bus='0x03' slot='0x00' function='0x0'/>
    </controller>
    <interface type='network'>
      <mac address='52:54:00:f2:40:00'/>
      <source network='default'/>
      <model type='virtio'/>
      <link state='up'/>
      <address type='pci' domain='0x0000' bus='0x06' slot='0x00' function='0x0'/>
    </interface>
    <serial type='pty'>
      <target type='isa-serial' port='0'>
        <model name='isa-serial'/>
      </target>
    </serial>
    <console type='pty'>
      <target type='serial' port='0'/>
    </console>
    <input type='mouse' bus='ps2'/>
    <input type='keyboard' bus='ps2'/>
    <audio id='1' type='none'/>
    <hostdev mode='subsystem' type='pci' managed='yes'>
      <source>
        <address domain='0x0000' bus='0x28' slot='0x00' function='0x0'/>
      </source>
      <rom file='/home/muni/.local/share/libvirt/images/RX5600XT.rom'/>
      <address type='pci' domain='0x0000' bus='0x07' slot='0x00' function='0x0'/>
    </hostdev>
    <hostdev mode='subsystem' type='pci' managed='yes'>
      <source>
        <address domain='0x0000' bus='0x28' slot='0x00' function='0x1'/>
      </source>
      <rom file='/home/muni/.local/share/libvirt/images/RX5600XT.rom'/>
      <address type='pci' domain='0x0000' bus='0x09' slot='0x00' function='0x0'/>
    </hostdev>
    <hostdev mode='subsystem' type='usb' managed='yes'>
      <source>
        <vendor id='0x1532'/>
        <product id='0x025e'/>
      </source>
      <address type='usb' bus='0' port='4'/>
    </hostdev>
    <hostdev mode='subsystem' type='usb' managed='yes'>
      <source>
        <vendor id='0x1532'/>
        <product id='0x0f2a'/>
      </source>
      <address type='usb' bus='0' port='5'/>
    </hostdev>
    <hostdev mode='subsystem' type='usb' managed='yes'>
      <source>
        <vendor id='0x1532'/>
        <product id='0x0f20'/>
      </source>
      <address type='usb' bus='0' port='6'/>
    </hostdev>
    <hostdev mode='subsystem' type='usb' managed='yes'>
      <source>
        <vendor id='0x046d'/>
        <product id='0xc52b'/>
      </source>
      <address type='usb' bus='0' port='7'/>
    </hostdev>
    <memballoon model='virtio'>
      <address type='pci' domain='0x0000' bus='0x05' slot='0x00' function='0x0'/>
    </memballoon>
  </devices>
</domain>
